python_ssr/__init__.py
python_ssr/api_client.py
python_ssr/site_renderer.py
python_ssr/storage.py
python_ssr/watch.py
python_ssr-0.0.4.dist-info/LICENSE
python_ssr-0.0.4.dist-info/METADATA
python_ssr-0.0.4.dist-info/WHEEL
python_ssr-0.0.4.dist-info/entry_points.txt
python_ssr-0.0.4.dist-info/top_level.txt
python_ssr-0.0.4.dist-info/RECORD
