Metadata-Version: 2.1
Name: python-ssr
Version: 0.0.4
Summary: A Python SSR library for dynamically rendering static websites
Home-page: https://github.com/kayon-ariel/Python-SSR
Author: Kayon Ariel
Author-email: kayonariel@gmail.com
License: MIT
Project-URL: Homepage, https://github.com/kayon-ariel/Python-SSR
Project-URL: Repository, https://github.com/kayon-ariel/Python-SSR.git
Project-URL: Issues, https://github.com/kayon-ariel/Python-SSR/issues
Keywords: python ssr,ssr,server side rendering,server-side-rendering
Classifier: Programming Language :: Python :: 3
Classifier: License :: OSI Approved :: MIT License
Classifier: Operating System :: OS Independent
Requires-Python: >=3.6
License-File: LICENSE
Requires-Dist: jinja2
Requires-Dist: requests
